omnidep/__init__.py
omnidep/__main__.py
omnidep/command.py
omnidep/errors.py
omnidep/imports.py
omnidep/main.py
omnidep/packages.py
omnidep/project.py
omnidep/tst/__init__.py
omnidep/tst/errors_test.py
omnidep/tst/imports_test.py
omnidep/tst/packages_test.py
omnidep/tst/project_test.py
omnidep/tst/test_cases/case_insensitive_sorted/pyproject.toml
omnidep/tst/test_cases/case_sensitive_sorted/pyproject.toml
omnidep/tst/test_cases/dependency_in_test_code/pyproject.toml
omnidep/tst/test_cases/dependency_in_test_code/tests/__init__.py
omnidep/tst/test_cases/dependency_in_test_code/tests/test_code.py
omnidep/tst/test_cases/dev_dependencies_new/pyproject.toml
omnidep/tst/test_cases/dev_dependencies_old/pyproject.toml
omnidep/tst/test_cases/every_import.py~
omnidep/tst/test_cases/failed_import/failed_import/__init__.py
omnidep/tst/test_cases/failed_import/failed_import/code.py
omnidep/tst/test_cases/failed_import/pyproject.toml
omnidep/tst/test_cases/failed_import_but_ignored/failed_import/__init__.py
omnidep/tst/test_cases/failed_import_but_ignored/failed_import/code.py
omnidep/tst/test_cases/failed_import_but_ignored/pyproject.toml
omnidep/tst/test_cases/namespace_none_declared/namespace_code/__init__.py
omnidep/tst/test_cases/namespace_none_declared/namespace_code/code.py
omnidep/tst/test_cases/namespace_none_declared/pyproject.toml
omnidep/tst/test_cases/namespace_one_declared/namespace_code/__init__.py
omnidep/tst/test_cases/namespace_one_declared/namespace_code/code.py
omnidep/tst/test_cases/namespace_one_declared/pyproject.toml
omnidep/tst/test_cases/namespace_three_declared/namespace_code/__init__.py
omnidep/tst/test_cases/namespace_three_declared/namespace_code/code.py
omnidep/tst/test_cases/namespace_three_declared/pyproject.toml
omnidep/tst/test_cases/parent_child_configured/parent_child/__init__.py
omnidep/tst/test_cases/parent_child_configured/parent_child/code.py
omnidep/tst/test_cases/parent_child_configured/pyproject.toml
omnidep-0.3.10.dist-info/entry_points.txt
omnidep-0.3.10.dist-info/LICENSE
omnidep-0.3.10.dist-info/METADATA
omnidep-0.3.10.dist-info/WHEEL
omnidep-0.3.10.dist-info/RECORD
