Metadata-Version: 2.1
Name: omnidep
Version: 0.3.10
Summary: Linter to compare project dependencies against imports in source code
Home-page: https://github.com/sjjessop/omnidep
License: MIT
Author: Steve Jessop
Author-email: 68118527+sjjessop@users.noreply.github.com
Requires-Python: >=3.8.1
Classifier: License :: OSI Approved :: MIT License
Classifier: Programming Language :: Python :: 3
Classifier: Programming Language :: Python :: 3.9
Classifier: Programming Language :: Python :: 3.10
Classifier: Programming Language :: Python :: 3.11
Classifier: Programming Language :: Python :: 3.12
Classifier: Programming Language :: Python :: 3.13
Classifier: Programming Language :: Python :: 3.14
Requires-Dist: isort (>=5.0.1) ; python_version < "3.10"
Requires-Dist: tomli (>=1.1.0) ; python_version < "3.11"
Project-URL: Changelog, https://github.com/sjjessop/omnidep/tree/develop#changelog
